{
  "hotels": [
    {
      "id": 0,
      "region": "Jastrzębia Góra",
      "name": "Jastrzębia Port",
      "price": "23 690 Kč / týden",
      "mapID": "kepataduma",
      "imgPath": "./res/hotels/jastrzebia_port.jpg",
      "rating": 4.75,
      "badges": [
        "wifi",
        "swimming-pool",
        "breakfast-in-price",
        "bikes"
      ],
      "gallery": [
        {
          "src": "./hotels/res/hotels/0/domek.jpg",
          "description": "Zadní strana domku"
        },
        {
          "src": "./hotels/res/hotels/0/herna.jpg",
          "description": "Herna pro děti"
        },
        {
          "src": "./hotels/res/hotels/0/posilovna.jpg",
          "description": "Posilovna"
        },
        {
          "src": "./hotels/res/hotels/0/restaurace.jpg",
          "description": "Restaurace"
        },
        {
          "src": "./hotels/res/hotels/0/bazen.jpg",
          "description": "Bazén"
        },
        {
          "src": "./hotels/res/hotels/0/plaz.jpg",
          "description": "Vstup na pláž"
        },
        {
          "src": "./hotels/res/hotels/0/vybaveni.jpg",
          "description": "Vybavení domácnosti"
        }
      ]
    },
    {
      "id": 1,
      "region": "Leba",
      "name": "Villa del Mar",
      "price": "17 223 Kč / týden",
      "imgPath": "./res/hotels/villa_del_mar.jpg",
      "rating": 4.55,
      "badges": [
        "wifi",
        "pets",
        "bikes"
      ],
      "gallery": [
        {
          "src": "./hotels/res/hotels/1/balkon.jpg",
          "description": "Balkón"
        },
        {
          "src": "./hotels/res/hotels/1/koupelna.jpg",
          "description": "Koupelna"
        },
        {
          "src": "./hotels/res/hotels/1/kuchyn.jpg",
          "description": "Kuchyň"
        },
        {
          "src": "./hotels/res/hotels/1/loznice.jpg",
          "description": "Ložnice"
        },
        {
          "src": "./hotels/res/hotels/1/posezeni.jpg",
          "description": "Venkovní posezení"
        },
        {
          "src": "./hotels/res/hotels/1/vila.jpg",
          "description": "Vila z přední strany"
        }
      ]
    },
    {
      "id": 2,
      "region": "Hel",
      "name": "Family Hel",
      "price": "30 292 Kč / týden",
      "imgPath": "./res/hotels/family_hel.jpg",
      "rating": 4.3,
      "badges": [
        "wifi",
        "swimming-pool",
        "half-food-in-price",
        "pets",
        "bikes"
      ],
      "gallery": [
        {
          "src": "./hotels/res/hotels/2/bazen.jpg",
          "description": "Bazén"
        },
        {
          "src": "./hotels/res/hotels/2/kuchyn.jpg",
          "description": "Kuchyň"
        },
        {
          "src": "./hotels/res/hotels/2/obyvaci_pokoj.jpg",
          "description": "Obývací pokoj"
        },
        {
          "src": "./hotels/res/hotels/2/plan_ubytovani.jpg",
          "description": "Plán ubytování"
        },
        {
          "src": "./hotels/res/hotels/2/plaz.jpg",
          "description": "Pláž"
        },
        {
          "src": "./hotels/res/hotels/2/podzemni_garaz.jpg",
          "description": "Podzemní garáž"
        },
        {
          "src": "./hotels/res/hotels/2/ubytovani.jpg",
          "description": "Ubytování"
        }
      ]
    },
    {
      "id": 3,
      "region": "Krakow",
      "name": "Radisson Blu",
      "price": "23 030 Kč / týden",
      "mapID": "kepataduma",
      "imgPath": "./res/hotels/atlantica_mikri_poli.jpg",
      "rating": 4.05,
      "badges": [
        "wifi",
        "swimming-pool",
        "breakfast-in-price",
        "bikes"
      ],
      "gallery": [
        {
          "src": "./hotels/res/hotels/0/domek.jpg",
          "description": "Zadní strana domku"
        },
        {
          "src": "./hotels/res/hotels/0/herna.jpg",
          "description": "Herna pro děti"
        },
        {
          "src": "./hotels/res/hotels/0/posilovna.jpg",
          "description": "Posilovna"
        },
        {
          "src": "./hotels/res/hotels/0/restaurace.jpg",
          "description": "Restaurace"
        },
        {
          "src": "./hotels/res/hotels/0/bazen.jpg",
          "description": "Bazén"
        },
        {
          "src": "./hotels/res/hotels/0/plaz.jpg",
          "description": "Vstup na pláž"
        },
        {
          "src": "./hotels/res/hotels/0/vybaveni.jpg",
          "description": "Vybavení domácnosti"
        }
      ]
    },
    {
      "id": 4,
      "region": "Krakow",
      "name": "The Bonerowski Palace",
      "price": "25 223 Kč / týden",
      "imgPath": "./res/hotels/belvedere.jpg",
      "rating": 3.1,
      "badges": [
        "wifi",
        "pets",
        "bikes"
      ],
      "gallery": [
        {
          "src": "./hotels/res/hotels/1/balkon.jpg",
          "description": "Balkón"
        },
        {
          "src": "./hotels/res/hotels/1/koupelna.jpg",
          "description": "Koupelna"
        },
        {
          "src": "./hotels/res/hotels/1/kuchyn.jpg",
          "description": "Kuchyň"
        },
        {
          "src": "./hotels/res/hotels/1/loznice.jpg",
          "description": "Ložnice"
        },
        {
          "src": "./hotels/res/hotels/1/posezeni.jpg",
          "description": "Venkovní posezení"
        },
        {
          "src": "./hotels/res/hotels/1/vila.jpg",
          "description": "Vila z přední strany"
        }
      ]
    },
    {
      "id": 5,
      "region": "Krakow",
      "name": "Sheraton Grand",
      "price": "27 292 Kč / týden",
      "imgPath": "./res/hotels/hermes.jpg",
      "rating": 4.4,
      "badges": [
        "wifi",
        "swimming-pool",
        "half-food-in-price",
        "pets",
        "bikes"
      ],
      "gallery": [
        {
          "src": "./hotels/res/hotels/2/bazen.jpg",
          "description": "Bazén"
        },
        {
          "src": "./hotels/res/hotels/2/kuchyn.jpg",
          "description": "Kuchyň"
        },
        {
          "src": "./hotels/res/hotels/2/obyvaci_pokoj.jpg",
          "description": "Obývací pokoj"
        },
        {
          "src": "./hotels/res/hotels/2/plan_ubytovani.jpg",
          "description": "Plán ubytování"
        },
        {
          "src": "./hotels/res/hotels/2/plaz.jpg",
          "description": "Pláž"
        },
        {
          "src": "./hotels/res/hotels/2/podzemni_garaz.jpg",
          "description": "Podzemní garáž"
        },
        {
          "src": "./hotels/res/hotels/2/ubytovani.jpg",
          "description": "Ubytování"
        }
      ]
    },
    {
      "id": 6,
      "region": "Krakow",
      "name": "Hotel Copernicus",
      "price": "10 323 Kč / týden",
      "mapID": "kepataduma",
      "imgPath": "./res/hotels/Random-House-image-1.jpg",
      "rating": 2.60,
      "badges": [
        "wifi",
        "swimming-pool",
        "breakfast-in-price",
        "bikes"
      ],
      "gallery": [
        {
          "src": "./hotels/res/hotels/0/domek.jpg",
          "description": "Zadní strana domku"
        },
        {
          "src": "./hotels/res/hotels/0/herna.jpg",
          "description": "Herna pro děti"
        },
        {
          "src": "./hotels/res/hotels/0/posilovna.jpg",
          "description": "Posilovna"
        },
        {
          "src": "./hotels/res/hotels/0/restaurace.jpg",
          "description": "Restaurace"
        },
        {
          "src": "./hotels/res/hotels/0/bazen.jpg",
          "description": "Bazén"
        },
        {
          "src": "./hotels/res/hotels/0/plaz.jpg",
          "description": "Vstup na pláž"
        },
        {
          "src": "./hotels/res/hotels/0/vybaveni.jpg",
          "description": "Vybavení domácnosti"
        }
      ]
    },
    {
      "id": 7,
      "region": "Krakow",
      "name": "PURO Krakow Stare Miasto",
      "price": "18 253 Kč / týden",
      "imgPath": "./res/hotels/Random-House-image-2.jpg",
      "rating": 4.55,
      "badges": [
        "wifi",
        "pets",
        "bikes"
      ],
      "gallery": [
        {
          "src": "./hotels/res/hotels/1/balkon.jpg",
          "description": "Balkón"
        },
        {
          "src": "./hotels/res/hotels/1/koupelna.jpg",
          "description": "Koupelna"
        },
        {
          "src": "./hotels/res/hotels/1/kuchyn.jpg",
          "description": "Kuchyň"
        },
        {
          "src": "./hotels/res/hotels/1/loznice.jpg",
          "description": "Ložnice"
        },
        {
          "src": "./hotels/res/hotels/1/posezeni.jpg",
          "description": "Venkovní posezení"
        },
        {
          "src": "./hotels/res/hotels/1/vila.jpg",
          "description": "Vila z přední strany"
        }
      ]
    },
    {
      "id": 8,
      "region": "Warsaw",
      "name": "Hotel Bristol",
      "price": "30 292 Kč / týden",
      "imgPath": "./res/hotels/Random-House-image-3.jpg",
      "rating": 4.3,
      "badges": [
        "wifi",
        "swimming-pool",
        "half-food-in-price",
        "pets",
        "bikes"
      ],
      "gallery": [
        {
          "src": "./hotels/res/hotels/2/bazen.jpg",
          "description": "Bazén"
        },
        {
          "src": "./hotels/res/hotels/2/kuchyn.jpg",
          "description": "Kuchyň"
        },
        {
          "src": "./hotels/res/hotels/2/obyvaci_pokoj.jpg",
          "description": "Obývací pokoj"
        },
        {
          "src": "./hotels/res/hotels/2/plan_ubytovani.jpg",
          "description": "Plán ubytování"
        },
        {
          "src": "./hotels/res/hotels/2/plaz.jpg",
          "description": "Pláž"
        },
        {
          "src": "./hotels/res/hotels/2/podzemni_garaz.jpg",
          "description": "Podzemní garáž"
        },
        {
          "src": "./hotels/res/hotels/2/ubytovani.jpg",
          "description": "Ubytování"
        }
      ]
    },
    {
      "id": 9,
      "region": "Warsaw",
      "name": "H15 Boutique Hotel",
      "price": "23 690 Kč / týden",
      "mapID": "kepataduma",
      "imgPath": "./res/hotels/Random-House-image-4.jpg",
      "rating": 4.75,
      "badges": [
        "wifi",
        "swimming-pool",
        "breakfast-in-price",
        "bikes"
      ],
      "gallery": [
        {
          "src": "./hotels/res/hotels/0/domek.jpg",
          "description": "Zadní strana domku"
        },
        {
          "src": "./hotels/res/hotels/0/herna.jpg",
          "description": "Herna pro děti"
        },
        {
          "src": "./hotels/res/hotels/0/posilovna.jpg",
          "description": "Posilovna"
        },
        {
          "src": "./hotels/res/hotels/0/restaurace.jpg",
          "description": "Restaurace"
        },
        {
          "src": "./hotels/res/hotels/0/bazen.jpg",
          "description": "Bazén"
        },
        {
          "src": "./hotels/res/hotels/0/plaz.jpg",
          "description": "Vstup na pláž"
        },
        {
          "src": "./hotels/res/hotels/0/vybaveni.jpg",
          "description": "Vybavení domácnosti"
        }
      ]
    },
    {
      "id": 10,
      "region": "Warsaw",
      "name": "Sofitel Victoria Warsaw",
      "price": "17 223 Kč / týden",
      "imgPath": "./res/hotels/10.jpg",
      "rating": 4.51,
      "badges": [
        "wifi",
        "pets",
        "bikes"
      ],
      "gallery": [
        {
          "src": "./hotels/res/hotels/1/balkon.jpg",
          "description": "Balkón"
        },
        {
          "src": "./hotels/res/hotels/1/koupelna.jpg",
          "description": "Koupelna"
        },
        {
          "src": "./hotels/res/hotels/1/kuchyn.jpg",
          "description": "Kuchyň"
        },
        {
          "src": "./hotels/res/hotels/1/loznice.jpg",
          "description": "Ložnice"
        },
        {
          "src": "./hotels/res/hotels/1/posezeni.jpg",
          "description": "Venkovní posezení"
        },
        {
          "src": "./hotels/res/hotels/1/vila.jpg",
          "description": "Vila z přední strany"
        }
      ]
    },
    {
      "id": 11,
      "region": "Warsaw",
      "name": "Raffles Europejski",
      "price": "30 520 Kč / týden",
      "imgPath": "./res/hotels/11.jpg",
      "rating": 4.27,
      "badges": [
        "wifi",
        "swimming-pool",
        "half-food-in-price",
        "pets",
        "bikes"
      ],
      "gallery": [
        {
          "src": "./hotels/res/hotels/2/bazen.jpg",
          "description": "Bazén"
        },
        {
          "src": "./hotels/res/hotels/2/kuchyn.jpg",
          "description": "Kuchyň"
        },
        {
          "src": "./hotels/res/hotels/2/obyvaci_pokoj.jpg",
          "description": "Obývací pokoj"
        },
        {
          "src": "./hotels/res/hotels/2/plan_ubytovani.jpg",
          "description": "Plán ubytování"
        },
        {
          "src": "./hotels/res/hotels/2/plaz.jpg",
          "description": "Pláž"
        },
        {
          "src": "./hotels/res/hotels/2/podzemni_garaz.jpg",
          "description": "Podzemní garáž"
        },
        {
          "src": "./hotels/res/hotels/2/ubytovani.jpg",
          "description": "Ubytování"
        }
      ]
    },
    {
      "id": 12,
      "region": "Warsaw",
      "name": "Nobu Hotel",
      "price": "22 900 Kč / týden",
      "mapID": "kepataduma",
      "imgPath": "./res/hotels/12.jpg",
      "rating": 4.75,
      "badges": [
        "wifi",
        "swimming-pool",
        "breakfast-in-price",
        "bikes"
      ],
      "gallery": [
        {
          "src": "./hotels/res/hotels/0/domek.jpg",
          "description": "Zadní strana domku"
        },
        {
          "src": "./hotels/res/hotels/0/herna.jpg",
          "description": "Herna pro děti"
        },
        {
          "src": "./hotels/res/hotels/0/posilovna.jpg",
          "description": "Posilovna"
        },
        {
          "src": "./hotels/res/hotels/0/restaurace.jpg",
          "description": "Restaurace"
        },
        {
          "src": "./hotels/res/hotels/0/bazen.jpg",
          "description": "Bazén"
        },
        {
          "src": "./hotels/res/hotels/0/plaz.jpg",
          "description": "Vstup na pláž"
        },
        {
          "src": "./hotels/res/hotels/0/vybaveni.jpg",
          "description": "Vybavení domácnosti"
        }
      ]
    },
    {
      "id": 13,
      "region": "Warsaw",
      "name": "InterContinental",
      "price": "16 302 Kč / týden",
      "imgPath": "./res/hotels/13.jpg",
      "rating": 4.79,
      "badges": [
        "wifi",
        "pets",
        "bikes"
      ],
      "gallery": [
        {
          "src": "./hotels/res/hotels/1/balkon.jpg",
          "description": "Balkón"
        },
        {
          "src": "./hotels/res/hotels/1/koupelna.jpg",
          "description": "Koupelna"
        },
        {
          "src": "./hotels/res/hotels/1/kuchyn.jpg",
          "description": "Kuchyň"
        },
        {
          "src": "./hotels/res/hotels/1/loznice.jpg",
          "description": "Ložnice"
        },
        {
          "src": "./hotels/res/hotels/1/posezeni.jpg",
          "description": "Venkovní posezení"
        },
        {
          "src": "./hotels/res/hotels/1/vila.jpg",
          "description": "Vila z přední strany"
        }
      ]
    },
    {
      "id": 14,
      "region": "Gdansk",
      "name": "Gdańsk Boutique",
      "price": "34 261 Kč / týden",
      "imgPath": "./res/hotels/14.jpg",
      "rating": 4.8,
      "badges": [
        "wifi",
        "swimming-pool",
        "half-food-in-price",
        "pets",
        "bikes"
      ],
      "gallery": [
        {
          "src": "./hotels/res/hotels/2/bazen.jpg",
          "description": "Bazén"
        },
        {
          "src": "./hotels/res/hotels/2/kuchyn.jpg",
          "description": "Kuchyň"
        },
        {
          "src": "./hotels/res/hotels/2/obyvaci_pokoj.jpg",
          "description": "Obývací pokoj"
        },
        {
          "src": "./hotels/res/hotels/2/plan_ubytovani.jpg",
          "description": "Plán ubytování"
        },
        {
          "src": "./hotels/res/hotels/2/plaz.jpg",
          "description": "Pláž"
        },
        {
          "src": "./hotels/res/hotels/2/podzemni_garaz.jpg",
          "description": "Podzemní garáž"
        },
        {
          "src": "./hotels/res/hotels/2/ubytovani.jpg",
          "description": "Ubytování"
        }
      ]
    },
    {
      "id": 15,
      "region": "Gdansk",
      "name": "Hotel Podewils",
      "price": "14 390 Kč / týden",
      "mapID": "kepataduma",
      "imgPath": "./res/hotels/15.jpg",
      "rating": 3.3,
      "badges": [
        "wifi",
        "swimming-pool",
        "breakfast-in-price",
        "bikes"
      ],
      "gallery": [
        {
          "src": "./hotels/res/hotels/0/domek.jpg",
          "description": "Zadní strana domku"
        },
        {
          "src": "./hotels/res/hotels/0/herna.jpg",
          "description": "Herna pro děti"
        },
        {
          "src": "./hotels/res/hotels/0/posilovna.jpg",
          "description": "Posilovna"
        },
        {
          "src": "./hotels/res/hotels/0/restaurace.jpg",
          "description": "Restaurace"
        },
        {
          "src": "./hotels/res/hotels/0/bazen.jpg",
          "description": "Bazén"
        },
        {
          "src": "./hotels/res/hotels/0/plaz.jpg",
          "description": "Vstup na pláž"
        },
        {
          "src": "./hotels/res/hotels/0/vybaveni.jpg",
          "description": "Vybavení domácnosti"
        }
      ]
    },
    {
      "id": 16,
      "region": "Gdansk",
      "name": "Dwór Oliwski",
      "price": "15 730 Kč / týden",
      "imgPath": "./res/hotels/16.jpg",
      "rating": 4.43,
      "badges": [
        "wifi",
        "pets",
        "bikes"
      ],
      "gallery": [
        {
          "src": "./hotels/res/hotels/1/balkon.jpg",
          "description": "Balkón"
        },
        {
          "src": "./hotels/res/hotels/1/koupelna.jpg",
          "description": "Koupelna"
        },
        {
          "src": "./hotels/res/hotels/1/kuchyn.jpg",
          "description": "Kuchyň"
        },
        {
          "src": "./hotels/res/hotels/1/loznice.jpg",
          "description": "Ložnice"
        },
        {
          "src": "./hotels/res/hotels/1/posezeni.jpg",
          "description": "Venkovní posezení"
        },
        {
          "src": "./hotels/res/hotels/1/vila.jpg",
          "description": "Vila z přední strany"
        }
      ]
    },
    {
      "id": 17,
      "region": "Gdansk",
      "name": "PURO Hotel Gdańsk Stare Miasto",
      "price": "27 554 Kč / týden",
      "imgPath": "./res/hotels/17.jpg",
      "rating": 3.98,
      "badges": [
        "wifi",
        "swimming-pool",
        "half-food-in-price",
        "pets",
        "bikes"
      ],
      "gallery": [
        {
          "src": "./hotels/res/hotels/2/bazen.jpg",
          "description": "Bazén"
        },
        {
          "src": "./hotels/res/hotels/2/kuchyn.jpg",
          "description": "Kuchyň"
        },
        {
          "src": "./hotels/res/hotels/2/obyvaci_pokoj.jpg",
          "description": "Obývací pokoj"
        },
        {
          "src": "./hotels/res/hotels/2/plan_ubytovani.jpg",
          "description": "Plán ubytování"
        },
        {
          "src": "./hotels/res/hotels/2/plaz.jpg",
          "description": "Pláž"
        },
        {
          "src": "./hotels/res/hotels/2/podzemni_garaz.jpg",
          "description": "Podzemní garáž"
        },
        {
          "src": "./hotels/res/hotels/2/ubytovani.jpg",
          "description": "Ubytování"
        }
      ]
    },
    {
      "id": 18,
      "region": "Gdansk",
      "name": "IBB Hotel Długi Targ",
      "price": "23 800 Kč / týden",
      "mapID": "kepataduma",
      "imgPath": "./res/hotels/18.jpg",
      "rating": 4.34,
      "badges": [
        "wifi",
        "swimming-pool",
        "breakfast-in-price",
        "bikes"
      ],
      "gallery": [
        {
          "src": "./hotels/res/hotels/0/domek.jpg",
          "description": "Zadní strana domku"
        },
        {
          "src": "./hotels/res/hotels/0/herna.jpg",
          "description": "Herna pro děti"
        },
        {
          "src": "./hotels/res/hotels/0/posilovna.jpg",
          "description": "Posilovna"
        },
        {
          "src": "./hotels/res/hotels/0/restaurace.jpg",
          "description": "Restaurace"
        },
        {
          "src": "./hotels/res/hotels/0/bazen.jpg",
          "description": "Bazén"
        },
        {
          "src": "./hotels/res/hotels/0/plaz.jpg",
          "description": "Vstup na pláž"
        },
        {
          "src": "./hotels/res/hotels/0/vybaveni.jpg",
          "description": "Vybavení domácnosti"
        }
      ]
    },
    {
      "id": 19,
      "region": "Gdansk",
      "name": "Hilton Gdansk",
      "price": "18 023 Kč / týden",
      "imgPath": "./res/hotels/19.jpg",
      "rating": 4.56,
      "badges": [
        "wifi",
        "pets",
        "bikes"
      ],
      "gallery": [
        {
          "src": "./hotels/res/hotels/1/balkon.jpg",
          "description": "Balkón"
        },
        {
          "src": "./hotels/res/hotels/1/koupelna.jpg",
          "description": "Koupelna"
        },
        {
          "src": "./hotels/res/hotels/1/kuchyn.jpg",
          "description": "Kuchyň"
        },
        {
          "src": "./hotels/res/hotels/1/loznice.jpg",
          "description": "Ložnice"
        },
        {
          "src": "./hotels/res/hotels/1/posezeni.jpg",
          "description": "Venkovní posezení"
        },
        {
          "src": "./hotels/res/hotels/1/vila.jpg",
          "description": "Vila z přední strany"
        }
      ]
    },
    {
      "id": 20,
      "region": "Gdansk",
      "name": "Dwór Oliwski City Hotel",
      "price": "31 393 Kč / týden",
      "imgPath": "./res/hotels/20.jpg",
      "rating": 4.45,
      "badges": [
        "wifi",
        "swimming-pool",
        "half-food-in-price",
        "pets",
        "bikes"
      ],
      "gallery": [
        {
          "src": "./hotels/res/hotels/2/bazen.jpg",
          "description": "Bazén"
        },
        {
          "src": "./hotels/res/hotels/2/kuchyn.jpg",
          "description": "Kuchyň"
        },
        {
          "src": "./hotels/res/hotels/2/obyvaci_pokoj.jpg",
          "description": "Obývací pokoj"
        },
        {
          "src": "./hotels/res/hotels/2/plan_ubytovani.jpg",
          "description": "Plán ubytování"
        },
        {
          "src": "./hotels/res/hotels/2/plaz.jpg",
          "description": "Pláž"
        },
        {
          "src": "./hotels/res/hotels/2/podzemni_garaz.jpg",
          "description": "Podzemní garáž"
        },
        {
          "src": "./hotels/res/hotels/2/ubytovani.jpg",
          "description": "Ubytování"
        }
      ]
    }
  ],
  "badges": {
    "wifi": {
      "img": "./res/wifi-signal.png",
      "text": "Wi-Fi zdarma"
    },
    "swimming-pool": {
      "img": "./res/swimming.png",
      "text": "Bazén"
    },
    "breakfast-in-price": {
      "img": "./res/croissant.png",
      "text": "Snídaně v ceně"
    },
    "bikes": {
      "img": "./res/bike.png",
      "text": "Půjčovna kol",
      "background": "true"
    },
    "pets": {
      "img": "./res/pets.png",
      "text": "Domácí mazlíčci vítáni"
    },
    "half-food-in-price": {
      "img": "./res/dish.png",
      "text": "Polopenze v ceně"
    }
  }
}